socket_proxy/__init__.py
socket_proxy/__main__.py
socket_proxy/api.py
socket_proxy/base.py
socket_proxy/bridge_server.py
socket_proxy/connection.py
socket_proxy/event.py
socket_proxy/expose_server.py
socket_proxy/package.py
socket_proxy/proxy.py
socket_proxy/py.typed
socket_proxy/tunnel.py
socket_proxy/tunnel_client.py
socket_proxy/tunnel_gui.py
socket_proxy/utils.py
socket_proxy-6.0.0.dist-info/licenses/LICENSE
socket_proxy-6.0.0.dist-info/METADATA
socket_proxy-6.0.0.dist-info/WHEEL
socket_proxy-6.0.0.dist-info/entry_points.txt
socket_proxy-6.0.0.dist-info/top_level.txt
socket_proxy-6.0.0.dist-info/RECORD
