Metadata-Version: 2.4
Name: socket-proxy
Version: 6.0.0
Summary: Proxy TCP ports of local systems
Home-page: https://github.com/fkantelberg/socket-proxy
Author: Florian Kantelberg
Author-email: florian.kantelberg@mailbox.org
License: MIT
Keywords: proxy socket network
Classifier: License :: OSI Approved :: MIT License
Classifier: Operating System :: OS Independent
Classifier: Programming Language :: Python :: 3
Requires-Python: >=3.9
License-File: LICENSE
Requires-Dist: typing_extensions
Provides-Extra: api
Requires-Dist: aiohttp; extra == "api"
Provides-Extra: event
Requires-Dist: aiohttp; extra == "event"
Dynamic: license-file
